nonebot_plugin_ImageLibrary/__init__.py
nonebot_plugin_imagelibrary-1.1.0.dist-info/licenses/LICENSE
nonebot_plugin_imagelibrary-1.1.0.dist-info/METADATA
nonebot_plugin_imagelibrary-1.1.0.dist-info/WHEEL
nonebot_plugin_imagelibrary-1.1.0.dist-info/entry_points.txt
nonebot_plugin_imagelibrary-1.1.0.dist-info/top_level.txt
nonebot_plugin_imagelibrary-1.1.0.dist-info/RECORD
